AUTHORS.txt
CHANGELOG.txt
LICENSE.txt
README.txt
setup.py
coinor/__init__.py
coinor.coopr.egg-info/PKG-INFO
coinor.coopr.egg-info/SOURCES.txt
coinor.coopr.egg-info/dependency_links.txt
coinor.coopr.egg-info/namespace_packages.txt
coinor.coopr.egg-info/requires.txt
coinor.coopr.egg-info/top_level.txt
coinor/coopr/__init__.py