Metadata-Version: 1.0
Name: coinor.coopr
Version: 2.4
Summary: COIN-OR project for Coopr
Home-page: https://projects.coin-or.org/CoinBazaar/wiki/Projects/coinor.coopr
Author: William Hart
Author-email: wehart@sandia.gov
License: BSD
Keywords: optimization
Platform: any
Classifier: Development Status :: 4 - Beta
Classifier: Intended Audience :: End Users/Desktop
Classifier: Intended Audience :: Science/Research
Classifier: License :: OSI Approved :: BSD License
Classifier: Natural Language :: English
Classifier: Operating System :: Microsoft :: Windows
Classifier: Operating System :: Unix
Classifier: Programming Language :: Python
Classifier: Programming Language :: Unix Shell
Classifier: Topic :: Scientific/Engineering :: Mathematics
Classifier: Topic :: Software Development :: Libraries :: Python Modules
Classifier: Topic :: Scientific/Engineering
